pynoorm/__init__.py
pynoorm/binder.py
pynoorm/debug.py
pynoorm/linker.py
pynoorm/overrides.py
pynoorm/utils.py
pynoorm-0.4.0.dist-info/METADATA
pynoorm-0.4.0.dist-info/RECORD
pynoorm-0.4.0.dist-info/WHEEL
pynoorm-0.4.0.dist-info/top_level.txt
