Metadata-Version: 2.1
Name: pynoorm
Version: 0.4.0
Summary: Use Python with or without an ORM.
Home-page: https://github.com/jpeyret/pynoorm
Author: JL Peyret
Author-email: jpeyret@gmail.com
License: MIT License
Keywords: sql database multiplatform
Platform: UNKNOWN
Classifier: Development Status :: 4 - Beta
Classifier: Intended Audience :: Developers
Classifier: License :: OSI Approved :: MIT License
Classifier: Natural Language :: English
Classifier: Programming Language :: Python :: 2
Classifier: Programming Language :: Python :: 2.7
Classifier: Programming Language :: Python :: 3
Classifier: Programming Language :: Python :: 3.3
Classifier: Programming Language :: Python :: 3.4
Classifier: Programming Language :: Python :: 3.5
Classifier: Programming Language :: Python :: 3.6
Classifier: Programming Language :: Python :: 3.7
Classifier: Topic :: Database :: Front-Ends
Classifier: Topic :: Utilities
Classifier: Operating System :: OS Independent
